<?xml version="1.0" encoding="utf-8"?>
<cms.alternativeform>
  <FormClassID>
    <CodeName>ecommerce.supplier</CodeName>
    <GUID>d30e1123-ea76-42db-8f74-a20da0c54d03</GUID>
    <ObjectType>cms.systemtable</ObjectType>
  </FormClassID>
  <FormCustomizedColumns />
  <FormDefinition>
    <form>
      <field column="SupplierSiteID" visible="true" order="6">
        <settings>
          <Options>
<![CDATA[
{%SiteContext.CurrentSiteID|(identity)GlobalAdministrator|(hash)9c39facc98736765cda9f794a5e39afc2f12d5ea5299715a63c306049620436c%};{$com.onthissiteonly$}
;{$com.globally$}
]]>
          </Options>
          <SortItems>False</SortItems>
          <EditText>False</EditText>
        </settings>
        <properties>
          <visiblemacro ismacro="true">
            <![CDATA[{%Settings.CMSStoreAllowGlobalSuppliers && CurrentUser.IsAuthorizedPerResource("CMS.Ecommerce","EcommerceGlobalModify") && (CurrentUser.IsAuthorizedPerResource("CMS.Ecommerce","ModifySuppliers") || CurrentUser.IsAuthorizedPerResource("CMS.Ecommerce","EcommerceModify"))|(identity)GlobalAdministrator|(hash)9522a9e6e05529e059dd9d728cd79dd80cc8877f743563414dbebd08126702b9%}]]>
          </visiblemacro>
          <defaultvalue ismacro="true">
<![CDATA[
{% if (!Settings.CMSStoreAllowGlobalSuppliers
    || !CurrentUser.IsAuthorizedPerResource("CMS.Ecommerce","EcommerceGlobalModify")
    || CurrentUser.IsAuthorizedPerResource("CMS.Ecommerce","ModifySuppliers")
    || CurrentUser.IsAuthorizedPerResource("CMS.Ecommerce","EcommerceModify")) {SiteContext.CurrentSiteID} |(identity)GlobalAdministrator|(hash)a29bbd4576eabbde4dbd8f1ca5747c618eae4e9b2c636b2e000b7bed9a02b03b%}
]]>
          </defaultvalue>
          <fieldcaption>{$com.available$}</fieldcaption>
        </properties>
      </field>
      <field column="SupplierEnabled" order="7" />
      <field column="SupplierGUID" order="8" />
      <field column="SupplierLastModified" order="9" />
    </form>
  </FormDefinition>
  <FormDisplayName>New</FormDisplayName>
  <FormGUID>ffa4eebb-d119-475a-88a1-57f41df1975f</FormGUID>
  <FormHideNewParentFields>False</FormHideNewParentFields>
  <FormIsCustom>False</FormIsCustom>
  <FormName>New</FormName>
</cms.alternativeform>