<?xml version="1.0" encoding="utf-8"?>
<cms.pageurlpath>
  <PageUrlPathCulture>es-ES</PageUrlPathCulture>
  <PageUrlPathGUID>83b16fd0-12de-408b-b255-0aded32908b4</PageUrlPathGUID>
  <PageUrlPathNodeID>
    <CodeName>/Store/Brewers/AeroPress</CodeName>
    <GUID>f869d687-8fa9-4b1c-b573-764ac0590d74</GUID>
    <ObjectType>cms.node</ObjectType>
    <Site>
      <CodeName>DancingGoatCore</CodeName>
      <GUID>80a391fd-3cfb-4bfa-ad6a-3ba33b79c632</GUID>
      <ObjectType>cms.site</ObjectType>
    </Site>
  </PageUrlPathNodeID>
  <PageUrlPathSiteID>
    <CodeName>DancingGoatCore</CodeName>
    <GUID>80a391fd-3cfb-4bfa-ad6a-3ba33b79c632</GUID>
    <ObjectType>cms.site</ObjectType>
  </PageUrlPathSiteID>
  <PageUrlPathUrlPath>es-ES/Store/Brewers/AeroPress</PageUrlPathUrlPath>
  <PageUrlPathUrlPathHash>
    <![CDATA[D5CD71070627C4F938DACD7A3A64503FFF4B44B8C1CC9E435862BFF156AE282F]]>
  </PageUrlPathUrlPathHash>
</cms.pageurlpath>