<?xml version="1.0" encoding="utf-8"?>
<cms.alternativeform>
  <FormClassID>
    <CodeName>ecommerce.manufacturer</CodeName>
    <GUID>dcbcbc29-fa72-404c-bcaf-7eea0dac144e</GUID>
    <ObjectType>cms.systemtable</ObjectType>
  </FormClassID>
  <FormCustomizedColumns />
  <FormDefinition>
    <form>
      <field column="ManufacturerThumbnailGUID" order="5" />
      <field column="ManufacturerSiteID" visible="true" order="6">
        <settings>
          <Options>
<![CDATA[
{%SiteContext.CurrentSiteID|(identity)GlobalAdministrator|(hash)9c39facc98736765cda9f794a5e39afc2f12d5ea5299715a63c306049620436c%};{$com.onthissiteonly$}
;{$com.globally$}
]]>
          </Options>
          <SortItems>False</SortItems>
          <EditText>False</EditText>
          <controlname>dropdownlistcontrol</controlname>
        </settings>
        <properties>
          <visiblemacro>
            <![CDATA[{%Settings.CMSStoreAllowGlobalManufacturers && CurrentUser.IsAuthorizedPerResource("CMS.Ecommerce","EcommerceGlobalModify") && (CurrentUser.IsAuthorizedPerResource("CMS.Ecommerce","ModifyManufacturers") || CurrentUser.IsAuthorizedPerResource("CMS.Ecommerce","EcommerceModify"))|(identity)GlobalAdministrator|(hash)6cc4a6009cb704770be3f8743c4b7a6381a91472a9a54506e81118b5d8193d5d%}]]>
          </visiblemacro>
          <defaultvalue ismacro="true">
<![CDATA[
{% if (!Settings.CMSStoreAllowGlobalManufacturers
    || !CurrentUser.IsAuthorizedPerResource("CMS.Ecommerce","EcommerceGlobalModify")
    || CurrentUser.IsAuthorizedPerResource("CMS.Ecommerce","ModifyManufacturers")
    || CurrentUser.IsAuthorizedPerResource("CMS.Ecommerce","EcommerceModify")) {SiteContext.CurrentSiteID} |(identity)GlobalAdministrator|(hash)4e1dedfbb353a2ef43b81a2899752083a3dc03b28b7ae269ab8877aba46c4a39%}
]]>
          </defaultvalue>
          <fieldcaption>{$com.available$}</fieldcaption>
        </properties>
      </field>
      <field column="ManufacturerLastModified" order="7" />
      <field column="ManufacturerEnabled" visible="">
        <settings>
          <controlname />
        </settings>
        <properties>
          <fieldcaption />
        </properties>
      </field>
    </form>
  </FormDefinition>
  <FormDisplayName>Quick add</FormDisplayName>
  <FormGUID>2e2bdff0-75cf-46b3-9841-e025385ae446</FormGUID>
  <FormHideNewParentFields>False</FormHideNewParentFields>
  <FormIsCustom>False</FormIsCustom>
  <FormName>quickadd</FormName>
</cms.alternativeform>